nag_b2b_api/Database.py
nag_b2b_api/__init__.py
nag_b2b_api_HalfBottleOfMind-0.0.2.dist-info/LICENSE
nag_b2b_api_HalfBottleOfMind-0.0.2.dist-info/METADATA
nag_b2b_api_HalfBottleOfMind-0.0.2.dist-info/WHEEL
nag_b2b_api_HalfBottleOfMind-0.0.2.dist-info/top_level.txt
nag_b2b_api_HalfBottleOfMind-0.0.2.dist-info/RECORD
